choose_models/__init__.py
choose_models/core.py
choose_models-0.0.2.dist-info/METADATA
choose_models-0.0.2.dist-info/WHEEL
choose_models-0.0.2.dist-info/top_level.txt
choose_models-0.0.2.dist-info/RECORD
