Metadata-Version: 2.4
Name: choose_models
Version: 0.0.2
Summary: Model selection CLI tool
Author-email: Foresty <dsparthsrivastava@email.com>
Requires-Python: >=3.8
Requires-Dist: numpy
Requires-Dist: pandas
Requires-Dist: plotly
